lambda_dev_server/__init__.py
lambda_dev_server/__main__.py
lambda_dev_server/_types.py
lambda_dev_server/_version.py
lambda_dev_server/py.typed
lambda_dev_server/simple_server.py
lambda_dev_server/wsgi.py
lambda_dev_server-0.0.7.dist-info/METADATA
lambda_dev_server-0.0.7.dist-info/WHEEL
lambda_dev_server-0.0.7.dist-info/entry_points.txt
lambda_dev_server-0.0.7.dist-info/licenses/LICENSE.txt
lambda_dev_server-0.0.7.dist-info/RECORD
